pyfuturedag/__init__.py
pyfuturedag/core.py
pyfuturedag-0.0.1.dist-info/LICENSE
pyfuturedag-0.0.1.dist-info/METADATA
pyfuturedag-0.0.1.dist-info/WHEEL
pyfuturedag-0.0.1.dist-info/top_level.txt
pyfuturedag-0.0.1.dist-info/RECORD
