Metadata-Version: 2.1
Name: pyfuturedag
Version: 0.0.1
Summary: Lightweight Python DAG implementation using asyncio futures
Author-email: Hao Hao Tan <helloharry66@gmail.com>
License: MIT License        
Project-URL: Homepage, https://github.com/gudgud96/pyfuturedag
Classifier: Programming Language :: Python :: 3
Classifier: License :: OSI Approved :: MIT License
Classifier: Operating System :: OS Independent
Requires-Python: >=3.7
License-File: LICENSE
